{
  "constructor": 0,
  "fields": [
    {
      "constructor": 0,
      "fields": [
        {
          "bytes": "39f29cfe6ab0765578a6e0d8871e1a3bc18f5d277b257095aabf1cd8"
        },
        {
          "bytes": ""
        }
      ]
    },
    {
      "constructor": 0,
      "fields": [
        {
          "bytes": "dfff8bc9cdfa7eb004eab6c303984b8e7b6f7cf3337f17826a23c1e2"
        },
        {
          "bytes": "001bc28000a5125631842958ab17da111bd82c01543c84083fed0be251a821a2"
        },
        {
          "int": 1
        }
      ]
    },
    {
      "constructor": 0,
      "fields": [
        {
          "bytes": "769c4c6e9bc3ba5406b9b89fb7beb6819e638ff2e2de63f008d5bcff"
        },
        {
          "bytes": "744e45574d"
        },
        {
          "int": 1
        }
      ]
    },
    {
      "int": 100000000
    }
  ]
}
